battlefy_toolkit/__init__.py
battlefy_toolkit/caching/TournamentLog.py
battlefy_toolkit/caching/__init__.py
battlefy_toolkit/caching/fileio.py
battlefy_toolkit/downloaders/__init__.py
battlefy_toolkit/downloaders/download_utils.py
battlefy_toolkit/downloaders/org_downloader.py
battlefy_toolkit/downloaders/tourney_downloader.py
battlefy_toolkit/endpoints/__init__.py
battlefy_toolkit/endpoints/addresses.py
battlefy_toolkit/objects/Standings.py
battlefy_toolkit/objects/Tournament.py
battlefy_toolkit/objects/TournamentInfo.py
battlefy_toolkit/objects/TournamentStage.py
battlefy_toolkit/objects/TournamentTeam.py
battlefy_toolkit/objects/__init__.py
battlefy_toolkit/org_lists/__init__.py
battlefy_toolkit/org_lists/splatoon_orgs.py
battlefy_toolkit/resolvers/DiscordIdResolver.py
battlefy_toolkit/resolvers/__init__.py
battlefy_toolkit/utils/__init__.py
battlefy_toolkit/utils/misc.py
battlefy_toolkit_Slate-1.3.0.dist-info/LICENSE
battlefy_toolkit_Slate-1.3.0.dist-info/METADATA
battlefy_toolkit_Slate-1.3.0.dist-info/WHEEL
battlefy_toolkit_Slate-1.3.0.dist-info/top_level.txt
battlefy_toolkit_Slate-1.3.0.dist-info/RECORD
