Metadata-Version: 2.1
Name: battlefy-toolkit-Slate
Version: 1.3.0
Summary: IPL Battlefy Toolkit
Home-page: https://github.com/IPLSplatoon/Battlefy-Toolkit
Author: IPL/Slate
Project-URL: Bug Reports, https://github.com/IPLSplatoon/Battlefy-Toolkit/issues
Project-URL: Source, https://github.com/IPLSplatoon/Battlefy-Toolkit/
Project-URL: Home, https://iplabs.ink/
Keywords: ipl,inkling performance labs,battlefy,splatoon,slate
Classifier: Development Status :: 3 - Alpha
Classifier: Intended Audience :: Developers
Classifier: Topic :: Software Development :: Build Tools
Classifier: Programming Language :: Python :: 3.9
Classifier: License :: OSI Approved :: MIT License
Classifier: Operating System :: OS Independent
Requires-Python: >=3.9, <4
License-File: LICENSE
